{
    "key": "group_6817db7cbec55",
    "title": "Feature - Newsroom Slider",
    "fields": [
        {
            "key": "field_6817db7c6e93d",
            "label": "Subtitle",
            "name": "subtitle",
            "aria-label": "",
            "type": "text",
            "instructions": "",
            "required": 0,
            "conditional_logic": 0,
            "wrapper": {
                "width": "",
                "class": "",
                "id": ""
            },
            "default_value": "",
            "maxlength": "",
            "allow_in_bindings": 0,
            "placeholder": "",
            "prepend": "",
            "append": ""
        },
        {
            "key": "field_6817dba06e93e",
            "label": "Title",
            "name": "title",
            "aria-label": "",
            "type": "text",
            "instructions": "",
            "required": 0,
            "conditional_logic": 0,
            "wrapper": {
                "width": "",
                "class": "",
                "id": ""
            },
            "default_value": "",
            "maxlength": "",
            "allow_in_bindings": 0,
            "placeholder": "",
            "prepend": "",
            "append": ""
        },
        {
            "key": "field_6817dbb66e93f",
            "label": "Link",
            "name": "link",
            "aria-label": "",
            "type": "link",
            "instructions": "",
            "required": 0,
            "conditional_logic": 0,
            "wrapper": {
                "width": "",
                "class": "",
                "id": ""
            },
            "return_format": "array",
            "allow_in_bindings": 0
        },
        {
            "key": "field_6817dbca6e940",
            "label": "News Slider",
            "name": "news_slider",
            "aria-label": "",
            "type": "repeater",
            "instructions": "",
            "required": 0,
            "conditional_logic": 0,
            "wrapper": {
                "width": "",
                "class": "",
                "id": ""
            },
            "layout": "block",
            "pagination": 0,
            "min": 0,
            "max": 0,
            "collapsed": "",
            "button_label": "Add News Slider",
            "rows_per_page": 20,
            "sub_fields": [
                {
                    "key": "field_6817dbdf6e941",
                    "label": "News",
                    "name": "news",
                    "aria-label": "",
                    "type": "post_object",
                    "instructions": "",
                    "required": 0,
                    "conditional_logic": 0,
                    "wrapper": {
                        "width": "",
                        "class": "",
                        "id": ""
                    },
                    "post_type": [
                        "post"
                    ],
                    "post_status": [
                        "publish"
                    ],
                    "taxonomy": "",
                    "return_format": "object",
                    "multiple": 0,
                    "allow_null": 0,
                    "allow_in_bindings": 0,
                    "bidirectional": 0,
                    "ui": 1,
                    "bidirectional_target": [],
                    "parent_repeater": "field_6817dbca6e940"
                }
            ]
        }
    ],
    "location": [
        [
            {
                "param": "post_type",
                "operator": "==",
                "value": "post"
            }
        ]
    ],
    "menu_order": 0,
    "position": "normal",
    "style": "default",
    "label_placement": "top",
    "instruction_placement": "label",
    "hide_on_screen": "",
    "active": false,
    "description": "",
    "show_in_rest": 0,
    "modified": 1749747734
}
